django_models_extensions/__init__.py
django_models_extensions/contrib/__init__.py
django_models_extensions/contrib/admin_buttons/__init__.py
django_models_extensions/contrib/admin_buttons/mixins.py
django_models_extensions/models/__init__.py
django_models_extensions/models/base.py
django_models_extensions/models/query.py
django_models_extensions/models/fields/__init__.py
django_models_extensions-0.0.3.dist-info/LICENSE
django_models_extensions-0.0.3.dist-info/METADATA
django_models_extensions-0.0.3.dist-info/WHEEL
django_models_extensions-0.0.3.dist-info/top_level.txt
django_models_extensions-0.0.3.dist-info/RECORD
