Metadata-Version: 2.1
Name: django-models-extensions
Version: 0.0.3
Summary: Models Extensions for Django.
Home-page: UNKNOWN
Author: lampofearth
Author-email: lampofearth@gmail.com
License: UNKNOWN
Project-URL: Documentation, https://github.com/lampofearth/django-models-extensions/wiki
Project-URL: Source, https://github.com/lampofearth/django-models-extensions/
Project-URL: Tracker, https://github.com/lampofearth/django-models-extensions/issues/
Platform: UNKNOWN
Classifier: Programming Language :: Python :: 3
Classifier: Framework :: Django
Classifier: License :: OSI Approved :: GNU General Public License (GPL)
Classifier: Operating System :: OS Independent
Classifier: Natural Language :: English
Requires-Python: >=3.6
Requires-Dist: django (>=2.0.0)
